<?xml version="1.0"?>
<!DOCTYPE hibernate-mapping PUBLIC "-//Hibernate/Hibernate Mapping DTD 3.0//EN"
"http://www.hibernate.org/dtd/hibernate-mapping-3.0.dtd">
<!-- Generated 2017/3/13 ?????? 09:50:40 by Hibernate Tools 4.3.1 -->
<hibernate-mapping>
    <class name="com.advantech.entity.Model" table="Model" schema="dbo" catalog="E_Document" optimistic-lock="version">
        <id name="id" type="int">
            <column name="id" />
            <generator class="assigned" />
        </id>
        <property name="name" type="string">
            <column name="name" length="50" not-null="true" />
        </property>
        <set name="sheetSpes" table="Sheet_SPE" inverse="true" lazy="true" fetch="select">
            <key>
                <column name="Model_id" />
            </key>
            <one-to-many class="com.advantech.entity.SheetSpe" />
        </set>
        <set name="sheetEes" table="Sheet_EE" inverse="true" lazy="true" fetch="select">
            <key>
                <column name="Model_id" />
            </key>
            <one-to-many class="com.advantech.entity.SheetEe" />
        </set>
        <set name="sheetIes" table="Sheet_IE" inverse="true" lazy="true" fetch="select">
            <key>
                <column name="Model_id" />
            </key>
            <one-to-many class="com.advantech.entity.SheetIe" />
        </set>
    </class>
</hibernate-mapping>
